asciiglet/__init__.py
asciiglet/__main__.py
asciiglet/abstract_object.py
asciiglet/emitter.py
asciiglet/environment.py
asciiglet/game_object.py
asciiglet/particle.py
asciiglet/particle_effect.py
asciiglet/sprite.py
asciiglet/transform.py
asciiglet/vector.py
asciiglet/examples/__init__.py
asciiglet/examples/charges.py
asciiglet/examples/clock.py
asciiglet/examples/fireworks.py
asciiglet/examples/fish.py
asciiglet/examples/rocket.py
asciiglet/examples/world_spinning.py
asciiglet-1.0.6.dist-info/LICENSE.txt
asciiglet-1.0.6.dist-info/METADATA
asciiglet-1.0.6.dist-info/WHEEL
asciiglet-1.0.6.dist-info/top_level.txt
asciiglet-1.0.6.dist-info/RECORD
