Metadata-Version: 2.1
Name: asciiglet
Version: 1.0.6
Summary: Asciiglet. For when you need to draw with text.
Home-page: https://github.com/LudwigVonChesterfield/Asciiglet
Author: Luduk
Author-email: ningawent@gmail.com
License: MIT
Platform: UNKNOWN
Classifier: License :: OSI Approved :: MIT License
Classifier: Programming Language :: Python :: 3
Classifier: Programming Language :: Python :: 3.7
Requires-Dist: pyglet
